{"number":"2039","name":"Articuno",
"imageUrl":"https://ettet1000.github.io/pokemon_test_new/images/2039.png",
"thumbnailUrl":"https://ettet1000.github.io/pokemon_test_new/images/2039_thumb.png",
"sprites":{"mainSpriteUrl":"https://ettet1000.github.io/pokemon_test_new/images/2039_main.png",
"frontAnimatedSpriteUrl":"https://ettet1000.github.io/pokemon_test_new/images/2039.gif",
"backAnimatedSpriteUrl":"https://ettet1000.github.io/pokemon_test_new/images/2039.gif",
"frontShinyAnimatedSpriteUrl":"https://ettet1000.github.io/pokemon_test_new/images/2039.gif",
"backShinyAnimatedSpriteUrl":"https://ettet1000.github.io/pokemon_test_new/images/2039.gif"},
"types":["Psychic","Flying"],"weaknesses":["Steel","Fire","Electric","Rock"],
"descriptions":["Known as Articuno, this Pokémon fires beams that can immobilize opponents as if they had been frozen solid."],
"specie":"Cruel","height":"50.9 kg (112.2 lbs)","weight":"1.7 m (5′07″)","breeding":{
"egg":{"groups":["No Eggs Discovered"],"cycle":"80 (20,304–20,560 steps)"},"genders":[{"type":"UNKNOWN"}]},
"training":{"evYield":"3 Special Attack","catchRate":"3 (0.4% with PokéBall, full HP)","baseFriendship":"35 ","baseExp":"261",
"growthRate":"Slow"},"abilities":[{"name":"Competitive","description":"상대가 사용하는 기술의 PP를 많이 줄인다."}],
"typesEffectiveness":{"Normal":"1","Fire":"1","Water":"1","Electric":"2","Grass":"½","Ice":"2","Fighting":"¼","Poison":"1","Ground":"0","Flying":"1","Psychic":"½","Bug":"1","Rock":"2","Ghost":"2","Dragon":"1","Dark":"2","Steel":"1","Fairy":"1"},
"evolutionChain":[{"number":"2039","name":"Articuno",
"imageUrl":"https://ettet1000.github.io/pokemon_test_new/images/2039.png","thumbUrl":"https://ettet1000.github.io/pokemon_test_new/images/2039_thumb.png","type":"FIRST"}],"previousEvolutions":[],"nextEvolutions":[],"superEvolutions":[],
"baseStats":{"hp":90,"attack":85,"defense":85,"spAtk":125,"spDef":100,"speed":95,"total":580},"cards":[{"number":"63","name":"Galarian Articuno","expansionName":"Evolving Skies",
"imageUrl":"https://pokedex.alansantos.dev/assets/pokemons/cards/144/SWSH7_EN_63.png"},{"number":"169","name":"Galarian Articuno V","expansionName":"Chilling Reign",
"imageUrl":"https://pokedex.alansantos.dev/assets/pokemons/cards/144/SWSH6_EN_169.png"},{"number":"170","name":"Galarian Articuno V","expansionName":"Chilling Reign",
"imageUrl":"https://pokedex.alansantos.dev/assets/pokemons/cards/144/SWSH6_EN_170.png"},{"number":"58","name":"Galarian Articuno V","expansionName":"Chilling Reign",
"imageUrl":"https://pokedex.alansantos.dev/assets/pokemons/cards/144/SWSH6_EN_58.png"},{"number":"SV54","name":"Articuno-GX","expansionName":"Yellow A Alternate",
"imageUrl":"https://pokedex.alansantos.dev/assets/pokemons/cards/144/SMA_EN_SV54.png"},{"number":"44","name":"Fire & Thunder & Articuno-GX","expansionName":"Hidden Fates",
"imageUrl":"https://pokedex.alansantos.dev/assets/pokemons/cards/144/SM115_EN_44.png"},{"number":"66","name":"Fire & Thunder & Articuno-GX","expansionName":"Hidden Fates",
"imageUrl":"https://pokedex.alansantos.dev/assets/pokemons/cards/144/SM115_EN_66.png"},{"number":"69","name":"Fire & Thunder & Articuno-GX","expansionName":"Hidden Fates",
"imageUrl":"https://pokedex.alansantos.dev/assets/pokemons/cards/144/SM115_EN_69.png"},{"number":"32","name":"Articuno","expansionName":"Team Up",
"imageUrl":"https://pokedex.alansantos.dev/assets/pokemons/cards/144/SM9_EN_32.png"},{"number":"154","name":"Articuno-GX","expansionName":"Celestial Storm",
"imageUrl":"https://pokedex.alansantos.dev/assets/pokemons/cards/144/SM7_EN_154.png"}],"soundUrl":"https://pokedex.alansantos.dev/assets/pokemons/sounds/144.mp3","moves":{
"levelUp":[
    {"level":1,
    "move":"Gust",
    "type":"Flying",
    "category":"Special",
    "power":"40",
    "accuracy":"100"},
    {"level":1,
    "move":"Psycho Shift",
    "type":"Psychic",
    "category":"Status",
    "power":"—",
    "accuracy":"100"},
    {"level":5,
    "move":"Confusion",
    "type":"Psychic",
    "category":"Special",
    "power":"50",
    "accuracy":"100"},
    {"level":10,
    "move":"Reflect",
    "type":"Psychic",
    "category":"Status",
    "power":"—",
    "accuracy":"—"},
    {"level":15,
    "move":"Hypnosis",
    "type":"Psychic",
    "category":"Status",
    "power":"—",
    "accuracy":"60"},
    {"level":20,
    "move":"Agility",
    "type":"Psychic",
    "category":"Status",
    "power":"—",
    "accuracy":"—"},
    {"level":25,
    "move":"Ancient Power",
    "type":"Rock",
    "category":"Special",
    "power":"60",
    "accuracy":"100"},
    {"level":30,
    "move":"Tailwind",
    "type":"Flying",
    "category":"Status",
    "power":"—",
    "accuracy":"—"},
    {"level":35,
    "move":"Psycho Cut",
    "type":"Psychic",
    "category":"Physical",
    "power":"70",
    "accuracy":"100"},
    {"level":40,
    "move":"Recover",
    "type":"Normal",
    "category":"Status",
    "power":"—",
    "accuracy":"—"},
    {"level":45,
    "move":"Freezing Glare",
    "type":"Psychic",
    "category":"Special",
    "power":"90",
    "accuracy":"100"},
    {"level":50,
    "move":"Dream Eater",
    "type":"Psychic",
    "category":"Special",
    "power":"100",
    "accuracy":"100"},
    {"level":55,
    "move":"Hurricane",
    "type":"Flying",
    "category":"Special",
    "power":"110",
    "accuracy":"70"},
    {"level":60,
    "move":"Mind Reader",
    "type":"Normal",
    "category":"Status",
    "power":"—",
    "accuracy":"—"},
    {"level":65,
    "move":"Future Sight",
    "type":"Psychic",
    "category":"Special",
    "power":"120",
    "accuracy":"100"},
    {"level":70,
    "move":"Trick Room",
    "type":"Psychic",
    "category":"Status",
    "power":"—",
    "accuracy":"—"}
]
,"technicalMachine":[
    {"technicalMachine":6,
    "move":"Fly",
    "type":"Flying",
    "category":"Physical",
    "power":"90",
    "accuracy":"95"},
    {"technicalMachine":8,
    "move":"Hyper Beam",
    "type":"Normal",
    "category":"Special",
    "power":"150",
    "accuracy":"90"},
    {"technicalMachine":9,
    "move":"Giga Impact",
    "type":"Normal",
    "category":"Physical",
    "power":"150",
    "accuracy":"90"},
    {"technicalMachine":17,
    "move":"Light Screen",
    "type":"Psychic",
    "category":"Status",
    "power":"—",
    "accuracy":"—"},
    {"technicalMachine":18,
    "move":"Reflect",
    "type":"Psychic",
    "category":"Status",
    "power":"—",
    "accuracy":"—"},
    {"technicalMachine":21,
    "move":"Rest",
    "type":"Psychic",
    "category":"Status",
    "power":"—",
    "accuracy":"—"},
    {"technicalMachine":24,
    "move":"Snore",
    "type":"Normal",
    "category":"Special",
    "power":"50",
    "accuracy":"100"},
    {"technicalMachine":25,
    "move":"Protect",
    "type":"Normal",
    "category":"Status",
    "power":"—",
    "accuracy":"—"},
    {"technicalMachine":26,
    "move":"Scary Face",
    "type":"Normal",
    "category":"Status",
    "power":"—",
    "accuracy":"100"},
    {"technicalMachine":30,
    "move":"Steel Wing",
    "type":"Steel",
    "category":"Physical",
    "power":"70",
    "accuracy":"90"},
    {"technicalMachine":39,
    "move":"Facade",
    "type":"Normal",
    "category":"Physical",
    "power":"70",
    "accuracy":"100"},
    {"technicalMachine":40,
    "move":"Swift",
    "type":"Normal",
    "category":"Special",
    "power":"60",
    "accuracy":"—"},
    {"technicalMachine":44,
    "move":"Imprison",
    "type":"Psychic",
    "category":"Status",
    "power":"—",
    "accuracy":"—"},
    {"technicalMachine":56,
    "move":"U-turn",
    "type":"Bug",
    "category":"Physical",
    "power":"70",
    "accuracy":"100"},
    {"technicalMachine":60,
    "move":"Power Swap",
    "type":"Psychic",
    "category":"Status",
    "power":"—",
    "accuracy":"—"},
    {"technicalMachine":61,
    "move":"Guard Swap",
    "type":"Psychic",
    "category":"Status",
    "power":"—",
    "accuracy":"—"},
    {"technicalMachine":69,
    "move":"Psycho Cut",
    "type":"Psychic",
    "category":"Physical",
    "power":"70",
    "accuracy":"100"},
    {"technicalMachine":70,
    "move":"Trick Room",
    "type":"Psychic",
    "category":"Status",
    "power":"—",
    "accuracy":"—"},
    {"technicalMachine":76,
    "move":"Round",
    "type":"Normal",
    "category":"Special",
    "power":"60",
    "accuracy":"100"},
    {"technicalMachine":95,
    "move":"Air Slash",
    "type":"Flying",
    "category":"Special",
    "power":"75",
    "accuracy":"95"}
],"technicalRecords":[
    {"technicalRecord":11,
    "move":"Psychic",
    "type":"Psychic",
    "category":"Special",
    "power":"90",
    "accuracy":"100"},
    {"technicalRecord":12,
    "move":"Agility",
    "type":"Psychic",
    "category":"Status",
    "power":"—",
    "accuracy":"—"},
    {"technicalRecord":20,
    "move":"Substitute",
    "type":"Normal",
    "category":"Status",
    "power":"—",
    "accuracy":"—"},
    {"technicalRecord":25,
    "move":"Psyshock",
    "type":"Psychic",
    "category":"Special",
    "power":"80",
    "accuracy":"100"},
    {"technicalRecord":26,
    "move":"Endure",
    "type":"Normal",
    "category":"Status",
    "power":"—",
    "accuracy":"—"},
    {"technicalRecord":27,
    "move":"Sleep Talk",
    "type":"Normal",
    "category":"Status",
    "power":"—",
    "accuracy":"—"},
    {"technicalRecord":33,
    "move":"Shadow Ball",
    "type":"Ghost",
    "category":"Special",
    "power":"80",
    "accuracy":"100"},
    {"technicalRecord":34,
    "move":"Future Sight",
    "type":"Psychic",
    "category":"Special",
    "power":"120",
    "accuracy":"100"},
    {"technicalRecord":40,
    "move":"Skill Swap",
    "type":"Psychic",
    "category":"Status",
    "power":"—",
    "accuracy":"—"},
    {"technicalRecord":42,
    "move":"Hyper Voice",
    "type":"Normal",
    "category":"Special",
    "power":"90",
    "accuracy":"100"},
    {"technicalRecord":49,
    "move":"Calm Mind",
    "type":"Psychic",
    "category":"Status",
    "power":"—",
    "accuracy":"—"},
    {"technicalRecord":66,
    "move":"Brave Bird",
    "type":"Flying",
    "category":"Physical",
    "power":"120",
    "accuracy":"100"},
    {"technicalRecord":82,
    "move":"Stored Power",
    "type":"Psychic",
    "category":"Special",
    "power":"20",
    "accuracy":"100"},
    {"technicalRecord":83,
    "move":"Ally Switch",
    "type":"Psychic",
    "category":"Status",
    "power":"—",
    "accuracy":"—"},
    {"technicalRecord":89,
    "move":"Hurricane",
    "type":"Flying",
    "category":"Special",
    "power":"110",
    "accuracy":"70"}
]
,"egg":[]
,"tutor":[
    {"move":"Dual Wingbeat",
    "type":"Flying",
    "category":"Physical",
    "power":"40",
    "accuracy":"90"},
    {"move":"Expanding Force",
    "type":"Psychic",
    "category":"Special",
    "power":"80",
    "accuracy":"100"}
]
,"evolution":[],"preEvolution":[]},"generation":"GALAR"}