{"number":"312","name":"Minun","imageUrl":"https://pokedex.alansantos.dev/assets/pokemons/images/312.png","thumbnailUrl":"https://pokedex.alansantos.dev/assets/pokemons/thumbs/312.png","sprites":{"mainSpriteUrl":"https://pokedex.alansantos.dev/assets/pokemons/sprites/312/312_main.png","frontAnimatedSpriteUrl":"https://pokedex.alansantos.dev/assets/pokemons/sprites/312/312_front_animated.gif","backAnimatedSpriteUrl":"https://pokedex.alansantos.dev/assets/pokemons/sprites/312/312_back_animated.gif","frontShinyAnimatedSpriteUrl":"https://pokedex.alansantos.dev/assets/pokemons/sprites/312/312_front_shiny_animated.gif","backShinyAnimatedSpriteUrl":"https://pokedex.alansantos.dev/assets/pokemons/sprites/312/312_back_shiny_animated.gif"},"types":["Electric"],"weaknesses":["Ground"],"descriptions":["Minun loves to cheer on its partner in battle. It gives off sparks from its body while it is doing so. If its partner is in trouble, this Pokémon gives off increasing amounts of sparks.","Minun is more concerned about cheering on its partners than its own safety. It shorts out the electricity in its body to create brilliant showers of sparks to cheer on its teammates."],"specie":"Cheering","height":"4.2 kg (9.3 lbs)","weight":"0.4 m (1′04″)","breeding":{"egg":{"groups":["Fairy"],"cycle":"20 (4,884–5,140 steps)"},"genders":[{"type":"MALE","percentage":"50%"},{"type":"FEMALE","percentage":"50%"}]},"training":{"evYield":"1 Speed","catchRate":"200 (26.1% with PokéBall, full HP)","baseFriendship":"50 (normal)","baseExp":"142","growthRate":"Medium Fast"},"abilities":[{"name":"Minus","description":"Boosts the Sp. Atk stat of the Pokémon if an ally with the Plus or Minus Ability is also in battle."}],"typesEffectiveness":{"Normal":"1","Fire":"1","Water":"1","Electric":"0","Grass":"1","Ice":"1","Fighting":"1","Poison":"1","Ground":"2","Flying":"½","Psychic":"1","Bug":"1","Rock":"1","Ghost":"1","Dragon":"1","Dark":"1","Steel":"½","Fairy":"1"},"evolutionChain":[{"number":"312","name":"Minun","imageUrl":"https://pokedex.alansantos.dev/assets/pokemons/images/312.png","thumbUrl":"https://pokedex.alansantos.dev/assets/pokemons/thumbs/312.png","type":"FIRST"}],"previousEvolutions":[],"nextEvolutions":[],"superEvolutions":[],"baseStats":{"hp":60,"attack":40,"defense":50,"spAtk":75,"spDef":85,"speed":95,"total":405},"cards":[{"number":"54","name":"Minun","expansionName":"Celestial Storm","imageUrl":"https://pokedex.alansantos.dev/assets/pokemons/cards/312/SM7_EN_54.png"},{"number":"34","name":"Minun","expansionName":"Shining Legends","imageUrl":"https://pokedex.alansantos.dev/assets/pokemons/cards/312/SM35_EN_34.png"},{"number":"32","name":"Minun","expansionName":"XY—Furious Fists","imageUrl":"https://pokedex.alansantos.dev/assets/pokemons/cards/312/XY3_EN_32.png"},{"number":"HGSS17","name":"Minun","expansionName":"HS—Promo","imageUrl":"https://pokedex.alansantos.dev/assets/pokemons/cards/312/HSP_EN_HGSS17.png"},{"number":"48","name":"Minun","expansionName":"Black & White—Legendary Treasures","imageUrl":"https://pokedex.alansantos.dev/assets/pokemons/cards/312/BW11_EN_48.png"},{"number":"40","name":"Minun","expansionName":"Black & White—Dark Explorers","imageUrl":"https://pokedex.alansantos.dev/assets/pokemons/cards/312/BW5_EN_40.png"},{"number":"34","name":"Minun","expansionName":"HS—Unleashed","imageUrl":"https://pokedex.alansantos.dev/assets/pokemons/cards/312/HGSS2_EN_34.png"},{"number":"7","name":"Minun","expansionName":"EX Dragon","imageUrl":"https://pokedex.alansantos.dev/assets/pokemons/cards/312/EX3_EN_7.png"},{"number":"12","name":"Minun","expansionName":"POP Series 1","imageUrl":"https://pokedex.alansantos.dev/assets/pokemons/cards/312/POP1_EN_12.png"},{"number":"67","name":"Minun","expansionName":"EX Hidden Legends","imageUrl":"https://pokedex.alansantos.dev/assets/pokemons/cards/312/EX5_EN_67.png"}],"soundUrl":"https://pokedex.alansantos.dev/assets/pokemons/sounds/312.mp3","moves":{"levelUp":[{"level":1,"category":"Status","move":"Growl","type":"Normal","power":"—","accuracy":"100"},{"level":1,"category":"Physical","move":"Nuzzle","type":"Electric","power":"20","accuracy":"100"},{"level":1,"category":"Status","move":"Play Nice","type":"Normal","power":"—","accuracy":"—"},{"level":1,"category":"Physical","move":"Quick Attack","type":"Normal","power":"40","accuracy":"100"},{"level":1,"category":"Status","move":"Thunder Wave","type":"Electric","power":"—","accuracy":"90"},{"level":4,"category":"Status","move":"Helping Hand","type":"Normal","power":"—","accuracy":"—"},{"level":7,"category":"Physical","move":"Spark","type":"Electric","power":"65","accuracy":"100"},{"level":10,"category":"Status","move":"Encore","type":"Normal","power":"—","accuracy":"100"},{"level":13,"category":"Status","move":"Switcheroo","type":"Dark","power":"—","accuracy":"100"},{"level":16,"category":"Special","move":"Swift","type":"Normal","power":"60","accuracy":"∞"},{"level":19,"category":"Special","move":"Electro Ball","type":"Electric","power":"—","accuracy":"100"},{"level":22,"category":"Status","move":"Copycat","type":"Normal","power":"—","accuracy":"—"},{"level":25,"category":"Status","move":"Fake Tears","type":"Dark","power":"—","accuracy":"100"},{"level":28,"category":"Status","move":"Charge","type":"Electric","power":"—","accuracy":"—"},{"level":31,"category":"Special","move":"Discharge","type":"Electric","power":"80","accuracy":"100"},{"level":34,"category":"Status","move":"Baton Pass","type":"Normal","power":"—","accuracy":"—"},{"level":37,"category":"Status","move":"Agility","type":"Psychic","power":"—","accuracy":"—"},{"level":40,"category":"Special","move":"Trump Card","type":"Normal","power":"—","accuracy":"∞"},{"level":43,"category":"Special","move":"Thunder","type":"Electric","power":"110","accuracy":"70"},{"level":46,"category":"Status","move":"Nasty Plot","type":"Dark","power":"—","accuracy":"—"},{"level":49,"category":"Status","move":"Entrainment","type":"Normal","power":"—","accuracy":"100"}],"technicalMachine":[{"technicalMachine":6,"category":"Status","move":"Toxic","type":"Poison","power":"—","accuracy":"90"},{"technicalMachine":10,"category":"Special","move":"Hidden Power","type":"Normal","power":"60","accuracy":"100"},{"technicalMachine":16,"category":"Status","move":"Light Screen","type":"Psychic","power":"—","accuracy":"—"},{"technicalMachine":17,"category":"Status","move":"Protect","type":"Normal","power":"—","accuracy":"—"},{"technicalMachine":18,"category":"Status","move":"Rain Dance","type":"Water","power":"—","accuracy":"—"},{"technicalMachine":21,"category":"Physical","move":"Frustration","type":"Normal","power":"—","accuracy":"100"},{"technicalMachine":24,"category":"Special","move":"Thunderbolt","type":"Electric","power":"90","accuracy":"100"},{"technicalMachine":25,"category":"Special","move":"Thunder","type":"Electric","power":"110","accuracy":"70"},{"technicalMachine":27,"category":"Physical","move":"Return","type":"Normal","power":"—","accuracy":"100"},{"technicalMachine":32,"category":"Status","move":"Double Team","type":"Normal","power":"—","accuracy":"—"},{"technicalMachine":42,"category":"Physical","move":"Facade","type":"Normal","power":"70","accuracy":"100"},{"technicalMachine":44,"category":"Status","move":"Rest","type":"Psychic","power":"—","accuracy":"—"},{"technicalMachine":45,"category":"Status","move":"Attract","type":"Normal","power":"—","accuracy":"100"},{"technicalMachine":48,"category":"Special","move":"Round","type":"Normal","power":"60","accuracy":"100"},{"technicalMachine":49,"category":"Special","move":"Echoed Voice","type":"Normal","power":"40","accuracy":"100"},{"technicalMachine":56,"category":"Physical","move":"Fling","type":"Dark","power":"—","accuracy":"100"},{"technicalMachine":57,"category":"Special","move":"Charge Beam","type":"Electric","power":"50","accuracy":"90"},{"technicalMachine":72,"category":"Special","move":"Volt Switch","type":"Electric","power":"70","accuracy":"100"},{"technicalMachine":73,"category":"Status","move":"Thunder Wave","type":"Electric","power":"—","accuracy":"90"},{"technicalMachine":86,"category":"Special","move":"Grass Knot","type":"Grass","power":"—","accuracy":"100"},{"technicalMachine":87,"category":"Status","move":"Swagger","type":"Normal","power":"—","accuracy":"85"},{"technicalMachine":88,"category":"Status","move":"Sleep Talk","type":"Normal","power":"—","accuracy":"—"},{"technicalMachine":90,"category":"Status","move":"Substitute","type":"Normal","power":"—","accuracy":"—"},{"technicalMachine":93,"category":"Physical","move":"Wild Charge","type":"Electric","power":"90","accuracy":"100"},{"technicalMachine":100,"category":"Status","move":"Confide","type":"Normal","power":"—","accuracy":"—"}],"technicalRecords":[],"egg":[{"category":"Status","move":"Charm","type":"Fairy","power":"—","accuracy":"100"},{"category":"Special","move":"Discharge","type":"Electric","power":"80","accuracy":"100"},{"category":"Status","move":"Fake Tears","type":"Dark","power":"—","accuracy":"100"},{"category":"Status","move":"Lucky Chant","type":"Normal","power":"—","accuracy":"—"},{"category":"Status","move":"Sing","type":"Normal","power":"—","accuracy":"55"},{"category":"Status","move":"Sweet Kiss","type":"Fairy","power":"—","accuracy":"75"},{"category":"Status","move":"Tearful Look","type":"Normal","power":"—","accuracy":"—"},{"category":"Status","move":"Wish","type":"Normal","power":"—","accuracy":"—"}],"tutor":[{"category":"Physical","move":"Covet","type":"Normal","power":"60","accuracy":"100"},{"category":"Special","move":"Electroweb","type":"Electric","power":"55","accuracy":"95"},{"category":"Status","move":"Helping Hand","type":"Normal","power":"—","accuracy":"—"},{"category":"Physical","move":"Iron Tail","type":"Steel","power":"100","accuracy":"75"},{"category":"Physical","move":"Last Resort","type":"Normal","power":"140","accuracy":"100"},{"category":"Status","move":"Magnet Rise","type":"Electric","power":"—","accuracy":"—"},{"category":"Special","move":"Shock Wave","type":"Electric","power":"60","accuracy":"∞"},{"category":"Special","move":"Signal Beam","type":"Bug","power":"75","accuracy":"100"},{"category":"Special","move":"Snore","type":"Normal","power":"50","accuracy":"100"},{"category":"Physical","move":"Thunder Punch","type":"Electric","power":"75","accuracy":"100"},{"category":"Special","move":"Uproar","type":"Normal","power":"90","accuracy":"100"}],"evolution":[],"preEvolution":[]},"generation":"GENERATION_III"}