{"number":"328","name":"Trapinch","imageUrl":"https://pokedex.alansantos.dev/assets/pokemons/images/328.png","thumbnailUrl":"https://pokedex.alansantos.dev/assets/pokemons/thumbs/328.png","sprites":{"mainSpriteUrl":"https://pokedex.alansantos.dev/assets/pokemons/sprites/328/328_main.png","frontAnimatedSpriteUrl":"https://pokedex.alansantos.dev/assets/pokemons/sprites/328/328_front_animated.gif","backAnimatedSpriteUrl":"https://pokedex.alansantos.dev/assets/pokemons/sprites/328/328_back_animated.gif","frontShinyAnimatedSpriteUrl":"https://pokedex.alansantos.dev/assets/pokemons/sprites/328/328_front_shiny_animated.gif","backShinyAnimatedSpriteUrl":"https://pokedex.alansantos.dev/assets/pokemons/sprites/328/328_back_shiny_animated.gif"},"types":["Ground"],"weaknesses":["Water","Grass","Ice"],"descriptions":["It makes an inescapable conical pit and lies in wait at the bottom for prey to come tumbling down.","Its nest is a sloped, bowl-like pit in the desert. Once something has fallen in, there is no escape."],"specie":"Ant Pit","height":"15.0 kg (33.1 lbs)","weight":"0.7 m (2′04″)","breeding":{"egg":{"groups":["Bug","Dragon"],"cycle":"20 (4,884–5,140 steps)"},"genders":[{"type":"MALE","percentage":"50%"},{"type":"FEMALE","percentage":"50%"}]},"training":{"evYield":"1 Attack","catchRate":"255 (33.3% with PokéBall, full HP)","baseFriendship":"50 (normal)","baseExp":"58","growthRate":"Medium Slow"},"abilities":[{"name":"Arena Trap","description":"Prevents opposing Pokémon from fleeing."},{"name":"Hyper Cutter","description":"The Pokémon's proud of its powerful pincers. They prevent other Pokémon from lowering its Attack stat."}],"typesEffectiveness":{"Normal":"1","Fire":"1","Water":"2","Electric":"0","Grass":"2","Ice":"2","Fighting":"1","Poison":"½","Ground":"1","Flying":"1","Psychic":"1","Bug":"1","Rock":"½","Ghost":"1","Dragon":"1","Dark":"1","Steel":"1","Fairy":"1"},"evolutionChain":[{"number":"328","name":"Trapinch","imageUrl":"https://pokedex.alansantos.dev/assets/pokemons/images/328.png","thumbUrl":"https://pokedex.alansantos.dev/assets/pokemons/thumbs/328.png","type":"FIRST"},{"number":"329","name":"Vibrava","imageUrl":"https://pokedex.alansantos.dev/assets/pokemons/images/329.png","thumbUrl":"https://pokedex.alansantos.dev/assets/pokemons/thumbs/329.png","type":"MIDDLE","requirement":"Level 35"},{"number":"330","name":"Flygon","imageUrl":"https://pokedex.alansantos.dev/assets/pokemons/images/330.png","thumbUrl":"https://pokedex.alansantos.dev/assets/pokemons/thumbs/330.png","type":"LAST","requirement":"Level 45"}],"previousEvolutions":[],"nextEvolutions":[{"number":"329","name":"Vibrava","imageUrl":"https://pokedex.alansantos.dev/assets/pokemons/images/329.png","thumbUrl":"https://pokedex.alansantos.dev/assets/pokemons/thumbs/329.png","type":"MIDDLE","requirement":"Level 35"},{"number":"330","name":"Flygon","imageUrl":"https://pokedex.alansantos.dev/assets/pokemons/images/330.png","thumbUrl":"https://pokedex.alansantos.dev/assets/pokemons/thumbs/330.png","type":"LAST","requirement":"Level 45"}],"superEvolutions":[],"baseStats":{"hp":45,"attack":100,"defense":45,"spAtk":45,"spDef":45,"speed":10,"total":290},"cards":[{"number":"40","name":"Trapinch","expansionName":"Shining Fates","imageUrl":"https://pokedex.alansantos.dev/assets/pokemons/cards/328/SWSH45_EN_40.png"},{"number":"89","name":"Trapinch","expansionName":"Darkness Ablaze","imageUrl":"https://pokedex.alansantos.dev/assets/pokemons/cards/328/SWSH3_EN_89.png"},{"number":"107","name":"Trapinch","expansionName":"Cosmic Eclipse","imageUrl":"https://pokedex.alansantos.dev/assets/pokemons/cards/328/SM12_EN_107.png"},{"number":"108","name":"Trapinch","expansionName":"Cosmic Eclipse","imageUrl":"https://pokedex.alansantos.dev/assets/pokemons/cards/328/SM12_EN_108.png"},{"number":"32","name":"Trapinch","expansionName":"Dragon Majesty","imageUrl":"https://pokedex.alansantos.dev/assets/pokemons/cards/328/SM75_EN_32.png"},{"number":"82","name":"Trapinch","expansionName":"XY—Primal Clash","imageUrl":"https://pokedex.alansantos.dev/assets/pokemons/cards/328/XY5_EN_82.png"},{"number":"53","name":"Trapinch","expansionName":"XY—Furious Fists","imageUrl":"https://pokedex.alansantos.dev/assets/pokemons/cards/328/XY3_EN_53.png"},{"number":"83","name":"Trapinch","expansionName":"Black & White—Boundaries Crossed","imageUrl":"https://pokedex.alansantos.dev/assets/pokemons/cards/328/BW7_EN_83.png"},{"number":"82","name":"Trapinch","expansionName":"EX Sandstorm","imageUrl":"https://pokedex.alansantos.dev/assets/pokemons/cards/328/EX2_EN_82.png"},{"number":"68","name":"Trapinch","expansionName":"EX Power Keepers","imageUrl":"https://pokedex.alansantos.dev/assets/pokemons/cards/328/EX16_EN_68.png"}],"soundUrl":"https://pokedex.alansantos.dev/assets/pokemons/sounds/328.mp3","moves":{"levelUp":[{"level":1,"category":"Physical","move":"Astonish","type":"Ghost","power":"30","accuracy":"100"},{"level":1,"category":"Status","move":"Sand Attack","type":"Ground","power":"—","accuracy":"100"},{"level":4,"category":"Status","move":"Laser Focus","type":"Normal","power":"—","accuracy":"—"},{"level":8,"category":"Physical","move":"Bite","type":"Dark","power":"60","accuracy":"100"},{"level":12,"category":"Special","move":"Mud-Slap","type":"Ground","power":"20","accuracy":"100"},{"level":16,"category":"Physical","move":"Sand Tomb","type":"Ground","power":"35","accuracy":"85"},{"level":20,"category":"Physical","move":"Bulldoze","type":"Ground","power":"60","accuracy":"100"},{"level":24,"category":"Physical","move":"Dig","type":"Ground","power":"80","accuracy":"100"},{"level":28,"category":"Physical","move":"Crunch","type":"Dark","power":"80","accuracy":"100"},{"level":32,"category":"Status","move":"Sandstorm","type":"Rock","power":"—","accuracy":"—"},{"level":36,"category":"Special","move":"Earth Power","type":"Ground","power":"90","accuracy":"100"},{"level":40,"category":"Physical","move":"Earthquake","type":"Ground","power":"100","accuracy":"100"},{"level":44,"category":"Physical","move":"Superpower","type":"Fighting","power":"120","accuracy":"100"},{"level":48,"category":"Physical","move":"Fissure","type":"Ground","power":"—","accuracy":"30"}],"technicalMachine":[{"technicalMachine":8,"category":"Special","move":"Hyper Beam","type":"Normal","power":"150","accuracy":"90"},{"technicalMachine":11,"category":"Special","move":"Solar Beam","type":"Grass","power":"120","accuracy":"100"},{"technicalMachine":15,"category":"Physical","move":"Dig","type":"Ground","power":"80","accuracy":"100"},{"technicalMachine":21,"category":"Status","move":"Rest","type":"Psychic","power":"—","accuracy":"—"},{"technicalMachine":22,"category":"Physical","move":"Rock Slide","type":"Rock","power":"75","accuracy":"90"},{"technicalMachine":24,"category":"Special","move":"Snore","type":"Normal","power":"50","accuracy":"100"},{"technicalMachine":25,"category":"Status","move":"Protect","type":"Normal","power":"—","accuracy":"—"},{"technicalMachine":28,"category":"Special","move":"Giga Drain","type":"Grass","power":"75","accuracy":"100"},{"technicalMachine":31,"category":"Status","move":"Attract","type":"Normal","power":"—","accuracy":"100"},{"technicalMachine":32,"category":"Status","move":"Sandstorm","type":"Rock","power":"—","accuracy":"—"},{"technicalMachine":34,"category":"Status","move":"Sunny Day","type":"Fire","power":"—","accuracy":"—"},{"technicalMachine":39,"category":"Physical","move":"Facade","type":"Normal","power":"70","accuracy":"100"},{"technicalMachine":48,"category":"Physical","move":"Rock Tomb","type":"Rock","power":"60","accuracy":"95"},{"technicalMachine":49,"category":"Physical","move":"Sand Tomb","type":"Ground","power":"35","accuracy":"85"},{"technicalMachine":53,"category":"Special","move":"Mud Shot","type":"Ground","power":"55","accuracy":"95"},{"technicalMachine":76,"category":"Special","move":"Round","type":"Normal","power":"60","accuracy":"100"},{"technicalMachine":81,"category":"Physical","move":"Bulldoze","type":"Ground","power":"60","accuracy":"100"}],"technicalRecords":[{"technicalRecord":1,"category":"Physical","move":"Body Slam","type":"Normal","power":"85","accuracy":"100"},{"technicalRecord":10,"category":"Physical","move":"Earthquake","type":"Ground","power":"100","accuracy":"100"},{"technicalRecord":13,"category":"Status","move":"Focus Energy","type":"Normal","power":"—","accuracy":"—"},{"technicalRecord":20,"category":"Status","move":"Substitute","type":"Normal","power":"—","accuracy":"—"},{"technicalRecord":26,"category":"Status","move":"Endure","type":"Normal","power":"—","accuracy":"—"},{"technicalRecord":27,"category":"Status","move":"Sleep Talk","type":"Normal","power":"—","accuracy":"—"},{"technicalRecord":32,"category":"Physical","move":"Crunch","type":"Dark","power":"80","accuracy":"100"},{"technicalRecord":39,"category":"Physical","move":"Superpower","type":"Fighting","power":"120","accuracy":"100"},{"technicalRecord":67,"category":"Special","move":"Earth Power","type":"Ground","power":"90","accuracy":"100"}],"egg":[{"category":"Physical","move":"Bug Bite","type":"Bug","power":"60","accuracy":"100"},{"category":"Physical","move":"Feint","type":"Normal","power":"30","accuracy":"100"},{"category":"Physical","move":"First Impression","type":"Bug","power":"90","accuracy":"100"},{"category":"Physical","move":"Flail","type":"Normal","power":"—","accuracy":"100"},{"category":"Physical","move":"Fury Cutter","type":"Bug","power":"40","accuracy":"95"},{"category":"Special","move":"Gust","type":"Flying","power":"40","accuracy":"100"},{"category":"Physical","move":"Quick Attack","type":"Normal","power":"40","accuracy":"100"}],"tutor":[{"category":"Special","move":"Scorching Sands","type":"Ground","power":"70","accuracy":"100"}],"evolution":[],"preEvolution":[]},"generation":"GENERATION_III"}