{"number":"360","name":"Wynaut","imageUrl":"https://pokedex.alansantos.dev/assets/pokemons/images/360.png","thumbnailUrl":"https://pokedex.alansantos.dev/assets/pokemons/thumbs/360.png","sprites":{"mainSpriteUrl":"https://pokedex.alansantos.dev/assets/pokemons/sprites/360/360_main.png","frontAnimatedSpriteUrl":"https://pokedex.alansantos.dev/assets/pokemons/sprites/360/360_front_animated.gif","backAnimatedSpriteUrl":"https://pokedex.alansantos.dev/assets/pokemons/sprites/360/360_back_animated.gif","frontShinyAnimatedSpriteUrl":"https://pokedex.alansantos.dev/assets/pokemons/sprites/360/360_front_shiny_animated.gif","backShinyAnimatedSpriteUrl":"https://pokedex.alansantos.dev/assets/pokemons/sprites/360/360_back_shiny_animated.gif"},"types":["Psychic"],"weaknesses":["Ghost","Dark","Bug"],"descriptions":["It tends to move in a pack with others. They cluster in a tight group to sleep in a cave.","It tends to move in a pack. Individuals squash against one another to toughen their spirits."],"specie":"Bright","height":"14.0 kg (30.9 lbs)","weight":"0.6 m (2′00″)","breeding":{"egg":{"groups":["Undiscovered"],"cycle":"20 (4,884–5,140 steps)"},"genders":[{"type":"MALE","percentage":"50%"},{"type":"FEMALE","percentage":"50%"}]},"training":{"evYield":"1 HP","catchRate":"125 (16.3% with PokéBall, full HP)","baseFriendship":"50 (normal)","baseExp":"52","growthRate":"Medium Fast"},"abilities":[{"name":"Shadow Tag","description":"This Pokémon steps on the opposing Pokémon's shadow to prevent it from escaping."}],"typesEffectiveness":{"Normal":"1","Fire":"1","Water":"1","Electric":"1","Grass":"1","Ice":"1","Fighting":"½","Poison":"1","Ground":"1","Flying":"1","Psychic":"½","Bug":"2","Rock":"1","Ghost":"2","Dragon":"1","Dark":"2","Steel":"1","Fairy":"1"},"evolutionChain":[{"number":"360","name":"Wynaut","imageUrl":"https://pokedex.alansantos.dev/assets/pokemons/images/360.png","thumbUrl":"https://pokedex.alansantos.dev/assets/pokemons/thumbs/360.png","type":"FIRST"},{"number":"202","name":"Wobbuffet","imageUrl":"https://pokedex.alansantos.dev/assets/pokemons/images/202.png","thumbUrl":"https://pokedex.alansantos.dev/assets/pokemons/thumbs/202.png","type":"LAST","requirement":"Level 15"}],"previousEvolutions":[],"nextEvolutions":[{"number":"202","name":"Wobbuffet","imageUrl":"https://pokedex.alansantos.dev/assets/pokemons/images/202.png","thumbUrl":"https://pokedex.alansantos.dev/assets/pokemons/thumbs/202.png","type":"LAST","requirement":"Level 15"}],"superEvolutions":[],"baseStats":{"hp":95,"attack":23,"defense":48,"spAtk":23,"spDef":48,"speed":23,"total":260},"cards":[{"number":"77","name":"Wynaut","expansionName":"Unified Minds","imageUrl":"https://pokedex.alansantos.dev/assets/pokemons/cards/360/SM11_EN_77.png"},{"number":"54","name":"Wynaut","expansionName":"EX Sandstorm","imageUrl":"https://pokedex.alansantos.dev/assets/pokemons/cards/360/EX2_EN_54.png"},{"number":"71","name":"Wynaut","expansionName":"EX Legend Maker","imageUrl":"https://pokedex.alansantos.dev/assets/pokemons/cards/360/EX12_EN_71.png"},{"number":"70","name":"Wynaut","expansionName":"EX Power Keepers","imageUrl":"https://pokedex.alansantos.dev/assets/pokemons/cards/360/EX16_EN_70.png"},{"number":"42","name":"Wynaut","expansionName":"Diamond & Pearl","imageUrl":"https://pokedex.alansantos.dev/assets/pokemons/cards/360/DP1_EN_42.png"}],"soundUrl":"https://pokedex.alansantos.dev/assets/pokemons/sounds/360.mp3","moves":{"levelUp":[{"level":1,"category":"Status","move":"Amnesia","type":"Psychic","power":"—","accuracy":"—"},{"level":1,"category":"Status","move":"Charm","type":"Fairy","power":"—","accuracy":"100"},{"level":1,"category":"Physical","move":"Counter","type":"Fighting","power":"—","accuracy":"100"},{"level":1,"category":"Status","move":"Destiny Bond","type":"Ghost","power":"—","accuracy":"—"},{"level":1,"category":"Status","move":"Encore","type":"Normal","power":"—","accuracy":"100"},{"level":1,"category":"Special","move":"Mirror Coat","type":"Psychic","power":"—","accuracy":"100"},{"level":1,"category":"Status","move":"Safeguard","type":"Normal","power":"—","accuracy":"—"},{"level":1,"category":"Status","move":"Splash","type":"Normal","power":"—","accuracy":"—"}],"technicalMachine":[{"technicalMachine":19,"category":"Status","move":"Safeguard","type":"Normal","power":"—","accuracy":"—"},{"technicalMachine":29,"category":"Status","move":"Charm","type":"Fairy","power":"—","accuracy":"100"}],"technicalRecords":[{"technicalRecord":17,"category":"Status","move":"Amnesia","type":"Psychic","power":"—","accuracy":"—"},{"technicalRecord":30,"category":"Status","move":"Encore","type":"Normal","power":"—","accuracy":"100"}],"egg":[],"tutor":[],"evolution":[],"preEvolution":[]},"generation":"GENERATION_III"}