{"number":"564","name":"Tirtouga","imageUrl":"https://pokedex.alansantos.dev/assets/pokemons/images/564.png","thumbnailUrl":"https://pokedex.alansantos.dev/assets/pokemons/thumbs/564.png","sprites":{"mainSpriteUrl":"https://pokedex.alansantos.dev/assets/pokemons/sprites/564/564_main.png","frontAnimatedSpriteUrl":"https://pokedex.alansantos.dev/assets/pokemons/sprites/564/564_front_animated.gif","backAnimatedSpriteUrl":"https://pokedex.alansantos.dev/assets/pokemons/sprites/564/564_back_animated.gif","frontShinyAnimatedSpriteUrl":"https://pokedex.alansantos.dev/assets/pokemons/sprites/564/564_front_shiny_animated.gif","backShinyAnimatedSpriteUrl":"https://pokedex.alansantos.dev/assets/pokemons/sprites/564/564_back_shiny_animated.gif"},"types":["Water","Rock"],"weaknesses":["Grass","Electric","Fighting","Ground"],"descriptions":["Tirtouga is considered to be the ancestor of many turtle Pokémon. It was restored to life from a fossil.","This Pokémon inhabited ancient seas. Although it can only crawl, it still comes up onto land in search of prey."],"specie":"Prototurtle","height":"16.5 kg (36.4 lbs)","weight":"0.7 m (2′04″)","breeding":{"egg":{"groups":["Water 1","Water 3"],"cycle":"30 (7,454–7,710 steps)"},"genders":[{"type":"MALE","percentage":"87.5%"},{"type":"FEMALE","percentage":"12.5%"}]},"training":{"evYield":"1 Defense","catchRate":"45 (5.9% with PokéBall, full HP)","baseFriendship":"50 (normal)","baseExp":"71","growthRate":"Medium Fast"},"abilities":[{"name":"Sturdy","description":"It cannot be knocked out with one hit. One-hit KO moves cannot knock it out, either."},{"name":"Solid Rock","description":"Reduces the power of supereffective attacks taken."}],"typesEffectiveness":{"Normal":"½","Fire":"¼","Water":"1","Electric":"2","Grass":"4","Ice":"½","Fighting":"2","Poison":"½","Ground":"2","Flying":"½","Psychic":"1","Bug":"1","Rock":"1","Ghost":"1","Dragon":"1","Dark":"1","Steel":"1","Fairy":"1"},"evolutionChain":[{"number":"564","name":"Tirtouga","imageUrl":"https://pokedex.alansantos.dev/assets/pokemons/images/564.png","thumbUrl":"https://pokedex.alansantos.dev/assets/pokemons/thumbs/564.png","type":"FIRST"},{"number":"565","name":"Carracosta","imageUrl":"https://pokedex.alansantos.dev/assets/pokemons/images/565.png","thumbUrl":"https://pokedex.alansantos.dev/assets/pokemons/thumbs/565.png","type":"LAST","requirement":"Level 37"}],"previousEvolutions":[],"nextEvolutions":[{"number":"565","name":"Carracosta","imageUrl":"https://pokedex.alansantos.dev/assets/pokemons/images/565.png","thumbUrl":"https://pokedex.alansantos.dev/assets/pokemons/thumbs/565.png","type":"LAST","requirement":"Level 37"}],"superEvolutions":[],"baseStats":{"hp":54,"attack":78,"defense":103,"spAtk":53,"spDef":45,"speed":22,"total":355},"cards":[{"number":"44","name":"Tirtouga","expansionName":"Unified Minds","imageUrl":"https://pokedex.alansantos.dev/assets/pokemons/cards/564/SM11_EN_44.png"},{"number":"27","name":"Tirtouga","expansionName":"Black & White—Plasma Blast","imageUrl":"https://pokedex.alansantos.dev/assets/pokemons/cards/564/BW10_EN_27.png"},{"number":"25","name":"Tirtouga","expansionName":"Black & White—Noble Victories","imageUrl":"https://pokedex.alansantos.dev/assets/pokemons/cards/564/BW3_EN_25.png"}],"soundUrl":"https://pokedex.alansantos.dev/assets/pokemons/sounds/564.mp3","moves":{"levelUp":[{"level":1,"category":"Special","move":"Water Gun","type":"Water","power":"40","accuracy":"100"},{"level":1,"category":"Status","move":"Withdraw","type":"Water","power":"—","accuracy":"—"},{"level":3,"category":"Status","move":"Protect","type":"Normal","power":"—","accuracy":"—"},{"level":6,"category":"Physical","move":"Aqua Jet","type":"Water","power":"40","accuracy":"100"},{"level":9,"category":"Physical","move":"Smack Down","type":"Rock","power":"50","accuracy":"100"},{"level":12,"category":"Special","move":"Ancient Power","type":"Rock","power":"60","accuracy":"100"},{"level":15,"category":"Physical","move":"Bite","type":"Dark","power":"60","accuracy":"100"},{"level":18,"category":"Status","move":"Wide Guard","type":"Rock","power":"—","accuracy":"—"},{"level":21,"category":"Special","move":"Brine","type":"Water","power":"65","accuracy":"100"},{"level":24,"category":"Physical","move":"Rock Slide","type":"Rock","power":"75","accuracy":"90"},{"level":27,"category":"Physical","move":"Crunch","type":"Dark","power":"80","accuracy":"100"},{"level":30,"category":"Status","move":"Curse","type":"Ghost","power":"—","accuracy":"—"},{"level":33,"category":"Status","move":"Iron Defense","type":"Steel","power":"—","accuracy":"—"},{"level":36,"category":"Physical","move":"Aqua Tail","type":"Water","power":"90","accuracy":"90"},{"level":39,"category":"Status","move":"Rain Dance","type":"Water","power":"—","accuracy":"—"},{"level":42,"category":"Special","move":"Hydro Pump","type":"Water","power":"110","accuracy":"80"},{"level":45,"category":"Status","move":"Shell Smash","type":"Normal","power":"—","accuracy":"—"}],"technicalMachine":[{"technicalMachine":15,"category":"Physical","move":"Dig","type":"Ground","power":"80","accuracy":"100"},{"technicalMachine":21,"category":"Status","move":"Rest","type":"Psychic","power":"—","accuracy":"—"},{"technicalMachine":22,"category":"Physical","move":"Rock Slide","type":"Rock","power":"75","accuracy":"90"},{"technicalMachine":24,"category":"Special","move":"Snore","type":"Normal","power":"50","accuracy":"100"},{"technicalMachine":25,"category":"Status","move":"Protect","type":"Normal","power":"—","accuracy":"—"},{"technicalMachine":27,"category":"Special","move":"Icy Wind","type":"Ice","power":"55","accuracy":"95"},{"technicalMachine":31,"category":"Status","move":"Attract","type":"Normal","power":"—","accuracy":"100"},{"technicalMachine":32,"category":"Status","move":"Sandstorm","type":"Rock","power":"—","accuracy":"—"},{"technicalMachine":33,"category":"Status","move":"Rain Dance","type":"Water","power":"—","accuracy":"—"},{"technicalMachine":36,"category":"Special","move":"Whirlpool","type":"Water","power":"35","accuracy":"85"},{"technicalMachine":39,"category":"Physical","move":"Facade","type":"Normal","power":"70","accuracy":"100"},{"technicalMachine":45,"category":"Physical","move":"Dive","type":"Water","power":"80","accuracy":"100"},{"technicalMachine":48,"category":"Physical","move":"Rock Tomb","type":"Rock","power":"60","accuracy":"95"},{"technicalMachine":53,"category":"Special","move":"Mud Shot","type":"Ground","power":"55","accuracy":"95"},{"technicalMachine":54,"category":"Physical","move":"Rock Blast","type":"Rock","power":"25","accuracy":"90"},{"technicalMachine":55,"category":"Special","move":"Brine","type":"Water","power":"65","accuracy":"100"},{"technicalMachine":61,"category":"Status","move":"Guard Swap","type":"Psychic","power":"—","accuracy":"—"},{"technicalMachine":76,"category":"Special","move":"Round","type":"Normal","power":"60","accuracy":"100"},{"technicalMachine":81,"category":"Physical","move":"Bulldoze","type":"Ground","power":"60","accuracy":"100"}],"technicalRecords":[{"technicalRecord":1,"category":"Physical","move":"Body Slam","type":"Normal","power":"85","accuracy":"100"},{"technicalRecord":3,"category":"Special","move":"Hydro Pump","type":"Water","power":"110","accuracy":"80"},{"technicalRecord":4,"category":"Special","move":"Surf","type":"Water","power":"90","accuracy":"100"},{"technicalRecord":5,"category":"Special","move":"Ice Beam","type":"Ice","power":"90","accuracy":"100"},{"technicalRecord":6,"category":"Special","move":"Blizzard","type":"Ice","power":"110","accuracy":"70"},{"technicalRecord":10,"category":"Physical","move":"Earthquake","type":"Ground","power":"100","accuracy":"100"},{"technicalRecord":16,"category":"Physical","move":"Waterfall","type":"Water","power":"80","accuracy":"100"},{"technicalRecord":20,"category":"Status","move":"Substitute","type":"Normal","power":"—","accuracy":"—"},{"technicalRecord":26,"category":"Status","move":"Endure","type":"Normal","power":"—","accuracy":"—"},{"technicalRecord":27,"category":"Status","move":"Sleep Talk","type":"Normal","power":"—","accuracy":"—"},{"technicalRecord":31,"category":"Physical","move":"Iron Tail","type":"Steel","power":"100","accuracy":"75"},{"technicalRecord":32,"category":"Physical","move":"Crunch","type":"Dark","power":"80","accuracy":"100"},{"technicalRecord":45,"category":"Special","move":"Muddy Water","type":"Water","power":"90","accuracy":"85"},{"technicalRecord":46,"category":"Status","move":"Iron Defense","type":"Steel","power":"—","accuracy":"—"},{"technicalRecord":67,"category":"Special","move":"Earth Power","type":"Ground","power":"90","accuracy":"100"},{"technicalRecord":69,"category":"Physical","move":"Zen Headbutt","type":"Psychic","power":"80","accuracy":"90"},{"technicalRecord":75,"category":"Physical","move":"Stone Edge","type":"Rock","power":"100","accuracy":"80"},{"technicalRecord":76,"category":"Status","move":"Stealth Rock","type":"Rock","power":"—","accuracy":"—"},{"technicalRecord":84,"category":"Special","move":"Scald","type":"Water","power":"80","accuracy":"100"},{"technicalRecord":98,"category":"Physical","move":"Liquidation","type":"Water","power":"85","accuracy":"100"}],"egg":[{"category":"Status","move":"Block","type":"Normal","power":"—","accuracy":"—"},{"category":"Physical","move":"Knock Off","type":"Dark","power":"65","accuracy":"100"},{"category":"Physical","move":"Rock Throw","type":"Rock","power":"50","accuracy":"90"},{"category":"Physical","move":"Rollout","type":"Rock","power":"30","accuracy":"90"},{"category":"Physical","move":"Slam","type":"Normal","power":"80","accuracy":"75"},{"category":"Special","move":"Water Pulse","type":"Water","power":"60","accuracy":"100"}],"tutor":[{"category":"Special","move":"Meteor Beam","type":"Rock","power":"120","accuracy":"90"}],"evolution":[],"preEvolution":[]},"generation":"GENERATION_V"}