{"number":"789","name":"Cosmog","imageUrl":"https://pokedex.alansantos.dev/assets/pokemons/images/789.png","thumbnailUrl":"https://pokedex.alansantos.dev/assets/pokemons/thumbs/789.png","sprites":{"mainSpriteUrl":"https://pokedex.alansantos.dev/assets/pokemons/sprites/789/789_main.png"},"types":["Psychic"],"weaknesses":["Ghost","Dark","Bug"],"descriptions":["Whether or not it’s a Pokémon from this world is a mystery. When it’s in a jam, it warps away to a safe place to hide.","Even though its helpless, gaseous body can be blown away by the slightest breeze, it doesn’t seem to care."],"specie":"Nebula","height":"0.1 kg (0.2 lbs)","weight":"0.2 m (0′08″)","breeding":{"egg":{"groups":["Undiscovered"],"cycle":"120 (30,584–30,840 steps)"},"genders":[{"type":"UNKNOWN"}]},"training":{"evYield":"1 HP","catchRate":"45 (5.9% with PokéBall, full HP)","baseFriendship":"0 (lower than normal)","baseExp":"40","growthRate":"Slow"},"abilities":[{"name":"Unaware","description":"When attacking, the Pokémon ignores the target Pokémon's stat changes."}],"typesEffectiveness":{"Normal":"1","Fire":"1","Water":"1","Electric":"1","Grass":"1","Ice":"1","Fighting":"½","Poison":"1","Ground":"1","Flying":"1","Psychic":"½","Bug":"2","Rock":"1","Ghost":"2","Dragon":"1","Dark":"2","Steel":"1","Fairy":"1"},"evolutionChain":[{"number":"789","name":"Cosmog","imageUrl":"https://pokedex.alansantos.dev/assets/pokemons/images/789.png","thumbUrl":"https://pokedex.alansantos.dev/assets/pokemons/thumbs/789.png","type":"FIRST"},{"number":"790","name":"Cosmoem","imageUrl":"https://pokedex.alansantos.dev/assets/pokemons/images/790.png","thumbUrl":"https://pokedex.alansantos.dev/assets/pokemons/thumbs/790.png","type":"MIDDLE","requirement":"Level 43"},{"number":"791","name":"Solgaleo","imageUrl":"https://pokedex.alansantos.dev/assets/pokemons/images/791.png","thumbUrl":"https://pokedex.alansantos.dev/assets/pokemons/thumbs/791.png","type":"LAST","requirement":"Level 53, in Pokémon Sun or Ultra Sun"},{"number":"792","name":"Lunala","imageUrl":"https://pokedex.alansantos.dev/assets/pokemons/images/792.png","thumbUrl":"https://pokedex.alansantos.dev/assets/pokemons/thumbs/792.png","type":"LAST","requirement":"Level 53, in Pokémon Moon or Ultra Moon"}],"previousEvolutions":[],"nextEvolutions":[{"number":"790","name":"Cosmoem","imageUrl":"https://pokedex.alansantos.dev/assets/pokemons/images/790.png","thumbUrl":"https://pokedex.alansantos.dev/assets/pokemons/thumbs/790.png","type":"MIDDLE","requirement":"Level 43"},{"number":"791","name":"Solgaleo","imageUrl":"https://pokedex.alansantos.dev/assets/pokemons/images/791.png","thumbUrl":"https://pokedex.alansantos.dev/assets/pokemons/thumbs/791.png","type":"LAST","requirement":"Level 53, in Pokémon Sun or Ultra Sun"},{"number":"792","name":"Lunala","imageUrl":"https://pokedex.alansantos.dev/assets/pokemons/images/792.png","thumbUrl":"https://pokedex.alansantos.dev/assets/pokemons/thumbs/792.png","type":"LAST","requirement":"Level 53, in Pokémon Moon or Ultra Moon"}],"superEvolutions":[],"baseStats":{"hp":43,"attack":29,"defense":31,"spAtk":29,"spDef":31,"speed":37,"total":200},"cards":[{"number":"100","name":"Cosmog","expansionName":"Cosmic Eclipse","imageUrl":"https://pokedex.alansantos.dev/assets/pokemons/cards/789/SM12_EN_100.png"},{"number":"99","name":"Cosmog","expansionName":"Cosmic Eclipse","imageUrl":"https://pokedex.alansantos.dev/assets/pokemons/cards/789/SM12_EN_99.png"},{"number":"100","name":"Cosmog","expansionName":"Unified Minds","imageUrl":"https://pokedex.alansantos.dev/assets/pokemons/cards/789/SM11_EN_100.png"},{"number":"69","name":"Cosmog","expansionName":"Team Up","imageUrl":"https://pokedex.alansantos.dev/assets/pokemons/cards/789/SM9_EN_69.png"},{"number":"60","name":"Cosmog","expansionName":"Ultra Prism","imageUrl":"https://pokedex.alansantos.dev/assets/pokemons/cards/789/SM5_EN_60.png"},{"number":"SM42","name":"Cosmog","expansionName":"Sun & Moon Promo","imageUrl":"https://pokedex.alansantos.dev/assets/pokemons/cards/789/SMP_EN_SM42.png"},{"number":"64","name":"Cosmog","expansionName":"Sun & Moon","imageUrl":"https://pokedex.alansantos.dev/assets/pokemons/cards/789/SM1_EN_64.png"}],"soundUrl":"https://pokedex.alansantos.dev/assets/pokemons/sounds/789.mp3","moves":{"levelUp":[{"level":1,"category":"Status","move":"Splash","type":"Normal","power":"—","accuracy":"—"},{"level":1,"category":"Status","move":"Teleport","type":"Psychic","power":"—","accuracy":"—"}],"technicalMachine":[],"technicalRecords":[],"egg":[],"tutor":[],"evolution":[],"preEvolution":[]},"generation":"GENERATION_VII"}